{
    "+@id": "5029",
    "+@gid": "1996729978",
    "+@type": "movie",
    "+@name": "Fist of the North Star: Legend of Kenshiro",
    "+@precision": "movie",
    "+@generated-on": "2024-12-04T20:21:55Z",
    "related-prev": {
        "+@rel": "part of",
        "+@id": "5024"
    },
    "info": [
        {
            "+@gid": "2314469822",
            "+@type": "Picture",
            "+@src": "https://cdn.animenewsnetwork.com/thumbnails/fit200x200/encyc/A5029-18.1469206928.jpg",
            "+@width": "143",
            "+@height": "200",
            "img": [
                {
                    "+@src": "https://cdn.animenewsnetwork.com/thumbnails/fit200x200/encyc/A5029-18.1469206928.jpg",
                    "+@width": "143",
                    "+@height": "200"
                },
                {
                    "+@src": "https://cdn.animenewsnetwork.com/thumbnails/max500x600/encyc/A5029-18.1469206928.jpg",
                    "+@width": "430",
                    "+@height": "600"
                },
                {
                    "+@src": "https://cdn.animenewsnetwork.com/images/encyc/A5029-18.1469206928.jpg",
                    "+@width": "460",
                    "+@height": "642"
                }
            ]
        },
        {
            "+content": "Fist of the North Star: Legend of Kenshiro",
            "+@gid": "3074865716",
            "+@type": "Main title",
            "+@lang": "EN"
        },
        {
            "+content": "El Puño de la Estrella del Norte: La leyenda de Kenshiro",
            "+@gid": "1098597467",
            "+@type": "Alternative title",
            "+@lang": "ES"
        },
        {
            "+content": "Fist of the North Star Zero: The Legend of Kenshiro",
            "+@gid": "2258412835",
            "+@type": "Alternative title",
            "+@lang": "EN"
        },
        {
            "+content": "Fist of the North Star: Legend of the True Savior - The Legend of Kenshiro",
            "+@gid": "1906138583",
            "+@type": "Alternative title",
            "+@lang": "EN"
        },
        {
            "+content": "Hokuto no Ken Zero - Kenshirō Den",
            "+@gid": "2215483029",
            "+@type": "Alternative title",
            "+@lang": "EN"
        },
        {
            "+content": "Ken il guerriero - La leggenda del vero salvatore",
            "+@gid": "1645581233",
            "+@type": "Alternative title",
            "+@lang": "IT"
        },
        {
            "+content": "Shin Kyūseishu Densetsu Hokuto no Ken Zero: Kenshirō-den",
            "+@gid": "3424114293",
            "+@type": "Alternative title",
            "+@lang": "JA"
        },
        {
            "+content": "Shin Kyūseishu Densetsu Hokuto no Ken: Kenshirō-den",
            "+@gid": "2280193656",
            "+@type": "Alternative title",
            "+@lang": "JA"
        },
        {
            "+content": "真救世主伝説 北斗の拳 ケンシロウ伝",
            "+@gid": "1210985847",
            "+@type": "Alternative title",
            "+@lang": "JA"
        },
        {
            "+content": "진구세주전설 북두의 권 ZERO : 켄시로전",
            "+@gid": "2072999011",
            "+@type": "Alternative title",
            "+@lang": "KO"
        },
        {
            "+content": "The story is about a catastrophic future in which most of the World, resources of Earth are destroyed after a nuclear war. Kenshiro, the next successor of the fierce fighting style Hokuto Shinken, is heavily wounded and his fiance is taken away by his friend Shin. The plot of the movie is the afterwards of this event. Kenshiro struggles to survive and help the village against their evil chief Siska. The story of this movie is about the unmentioned details in the originating story (Hokutou no Ken); which occurs between the first fight with Shin and the beginning of the series.",
            "+@gid": "2778459068",
            "+@type": "Plot Summary"
        },
        {
            "+content": "89",
            "+@gid": "1848585693",
            "+@type": "Running time"
        },
        {
            "+content": "2008-10-04 (Japan, Ikebukuro Cinema Sunshine limited preview)",
            "+@gid": "1181398970",
            "+@type": "Vintage"
        },
        {
            "+content": "2008-10-11 (Japan, nationwide premiere)",
            "+@gid": "2704002600",
            "+@type": "Premiere date"
        },
        {
            "+content": "#1: \"Hyakunen no Kodoku\" (百年の孤独) by Garnet Crow",
            "+@gid": "1038604070",
            "+@type": "Ending Theme"
        },
        {
            "+content": "#2: \"Theme from Fist of the North Star ~The Road of Lords~\" by Tak Matsumoto",
            "+@gid": "3495112818",
            "+@type": "Ending Theme"
        },
        {
            "+content": "\"Ai o Torimodose!! ~Movie ver.~\" (愛をとりもどせ!! 〜Movie ver.〜) by Crystal King",
            "+@gid": "1032173233",
            "+@type": "Insert song"
        }
    ],
    "ratings": {
        "+@nb_votes": "41",
        "+@weighted_score": "6.9241",
        "+@bayesian_score": "7.05735"
    },
    "release": {
        "+content": "Fist of the North Star: The Legend of Kenshirô (Blu-ray)",
        "+@date": "2024-03-26",
        "+@href": "https://www.animenewsnetwork.com/encyclopedia/releases.php?id=47238"
    },
    "news": [
        {
            "+content": "More Fist of the North Star",
            "+@datetime": "2005-02-27T16:55:27Z",
            "+@href": "https://www.animenewsnetwork.com/news/2005-02-27/more-fist-of-the-north-star"
        },
        {
            "+content": "<cite>Fist of the North Star</cite> Wedding Photos Posted Online",
            "+@datetime": "2008-09-17T03:59:00Z",
            "+@href": "https://www.animenewsnetwork.com/news/2008-09-16/fist-of-the-north-star-wedding-photos-posted-online"
        },
        {
            "+content": "Japanese Animation DVD Ranking, March 3-9",
            "+@datetime": "2009-03-11T03:23:48Z",
            "+@href": "https://www.animenewsnetwork.com/news/2009-03-10/japanese-animation-dvd-ranking-march-3-9"
        },
        {
            "+content": "Japanese Animation DVD Ranking, March 10-16",
            "+@datetime": "2009-03-18T03:57:00Z",
            "+@href": "https://www.animenewsnetwork.com/news/2009-03-17/japanese-animation-dvd-ranking-march-10-16"
        },
        {
            "+content": "Discotek Licenses <cite>Lovely Complex</cite> With New English Dub, <cite>Nanoha</cite>, <cite>Belladonna of Sadness</cite>, <cite>Chie the Brat</cite>, <cite>Rainbow</cite>, <cite>IGPX</cite>, More",
            "+@datetime": "2023-10-17T03:43:35Z",
            "+@href": "https://www.animenewsnetwork.com:/news/2023-10-16/discotek-licenses-lovely-complex-with-new-english-dub-nanoha-belladonna-of-sadness-chie-the-brat-/.203513"
        },
        {
            "+content": "North American Anime, Manga Releases, March 24-30",
            "+@datetime": "2024-03-27T21:00:00Z",
            "+@href": "https://www.animenewsnetwork.com:/news/2024-03-27/north-american-anime-manga-releases-march-24-30/.209261"
        }
    ],
    "staff": [
        {
            "+@gid": "1998084488",
            "task": "Director",
            "person": {
                "+content": "Toshiki Hirano",
                "+@id": "4688"
            }
        },
        {
            "+@gid": "2613865609",
            "task": "Screenplay",
            "person": {
                "+content": "Nobuhiko Horie",
                "+@id": "37754"
            }
        },
        {
            "+@gid": "3147457018",
            "task": "Storyboard",
            "person": {
                "+content": "Toshiki Hirano",
                "+@id": "4688"
            }
        },
        {
            "+@gid": "2074920627",
            "task": "Unit Director",
            "person": {
                "+content": "Jōhei Matsuura",
                "+@id": "3613"
            }
        },
        {
            "+@gid": "891958873",
            "task": "Unit Director",
            "person": {
                "+content": "Hideaki Oba",
                "+@id": "8840"
            }
        },
        {
            "+@gid": "2423143515",
            "task": "Unit Director",
            "person": {
                "+content": "Hijiri Sanpei",
                "+@id": "36866"
            }
        },
        {
            "+@gid": "961840707",
            "task": "Music",
            "person": {
                "+content": "Yuki Kajiura",
                "+@id": "3914"
            }
        },
        {
            "+@gid": "1355615650",
            "task": "Original Manga",
            "person": {
                "+content": "Tetsuo Hara",
                "+@id": "2444"
            }
        },
        {
            "+@gid": "2785070667",
            "task": "Original Manga",
            "person": {
                "+content": "Buronson",
                "+@id": "6984"
            }
        },
        {
            "+@gid": "226008270",
            "task": "Original Character Design",
            "person": {
                "+content": "Tetsuo Hara",
                "+@id": "2444"
            }
        },
        {
            "+@gid": "2952961134",
            "task": "Character Design",
            "person": {
                "+content": "Masaki Satō",
                "+@id": "8817"
            }
        },
        {
            "+@gid": "1246407126",
            "task": "Art Director",
            "person": {
                "+content": "Shunichiro Yoshihara",
                "+@id": "5940"
            }
        },
        {
            "+@gid": "729101571",
            "task": "Chief Animation Director",
            "person": {
                "+content": "Masaki Satō",
                "+@id": "8817"
            }
        },
        {
            "+@gid": "1710787926",
            "task": "Mechanical design",
            "person": {
                "+content": "Hisashi Eguchi",
                "+@id": "130746"
            }
        },
        {
            "+@gid": "2809462523",
            "task": "Sound Director",
            "person": {
                "+content": "Tōru Nakano",
                "+@id": "5945"
            }
        },
        {
            "+@gid": "1886874955",
            "task": "Director of Photography",
            "person": {
                "+content": "Masato Sato",
                "+@id": "182089"
            }
        },
        {
            "+@gid": "2391086277",
            "task": "Executive producer",
            "person": {
                "+content": "Kazuoki Onishi",
                "+@id": "176482"
            }
        },
        {
            "+@gid": "2303573389",
            "task": "Producer",
            "person": {
                "+content": "Kazuhiko Hitano",
                "+@id": "81036"
            }
        },
        {
            "+@gid": "1097190038",
            "task": "Producer",
            "person": {
                "+content": "Tomonari Katō",
                "+@id": "81037"
            }
        }
    ],
    "cast": [
        {
            "+@gid": "2142712584",
            "+@lang": "DE",
            "role": "Saya",
            "person": {
                "+content": "Gundi Eberhard",
                "+@id": "28955"
            }
        },
        {
            "+@gid": "979193947",
            "+@lang": "DE",
            "role": "Shisuka",
            "person": {
                "+content": "Jörg Döring",
                "+@id": "30094"
            }
        },
        {
            "+@gid": "2258050603",
            "+@lang": "DE",
            "role": "Jugai",
            "person": {
                "+content": "Jaron Löwenberg",
                "+@id": "30216"
            }
        },
        {
            "+@gid": "1022800637",
            "+@lang": "DE",
            "role": "Guruma",
            "person": {
                "+content": "Horst Lampe",
                "+@id": "30223"
            }
        },
        {
            "+@gid": "2432022431",
            "+@lang": "DE",
            "role": "Dan",
            "person": {
                "+content": "Jill Böttcher",
                "+@id": "30956"
            }
        },
        {
            "+@gid": "2721667151",
            "+@lang": "DE",
            "role": "Amo",
            "person": {
                "+content": "Anja Rybiczka",
                "+@id": "30959"
            }
        },
        {
            "+@gid": "771752875",
            "+@lang": "DE",
            "role": "Shin",
            "person": {
                "+content": "Alexander Doering",
                "+@id": "32431"
            }
        },
        {
            "+@gid": "2220920538",
            "+@lang": "DE",
            "role": "Ryuken",
            "person": {
                "+content": "Axel Lutter",
                "+@id": "46677"
            }
        },
        {
            "+@gid": "1134776955",
            "+@lang": "DE",
            "role": "Yuria",
            "person": {
                "+content": "Catrin Dams",
                "+@id": "46842"
            }
        },
        {
            "+@gid": "3099708472",
            "+@lang": "DE",
            "role": "Kenshirou",
            "person": {
                "+content": "Tobias Nath",
                "+@id": "63663"
            }
        },
        {
            "+@gid": "1551499501",
            "+@lang": "DE",
            "role": "Jinia",
            "person": {
                "+content": "Joachim Siebenschuh",
                "+@id": "140569"
            }
        },
        {
            "+@gid": "2593302329",
            "+@lang": "EN",
            "role": "Guruma",
            "person": {
                "+content": "Jeremy Inman",
                "+@id": "1117"
            }
        },
        {
            "+@gid": "2395242627",
            "+@lang": "EN",
            "role": "Ryuken",
            "person": {
                "+content": "Lex Lang",
                "+@id": "1143"
            }
        },
        {
            "+@gid": "1867613376",
            "+@lang": "EN",
            "role": "Jinia",
            "person": {
                "+content": "Michael Sorich",
                "+@id": "3050"
            }
        },
        {
            "+@gid": "1881813773",
            "+@lang": "EN",
            "role": "Yaman",
            "person": {
                "+content": "Doug Erholtz",
                "+@id": "4141"
            }
        },
        {
            "+@gid": "1891523639",
            "+@lang": "EN",
            "role": "Fugen",
            "person": {
                "+content": "Charlie Campbell",
                "+@id": "4788"
            }
        },
        {
            "+@gid": "1264121299",
            "+@lang": "EN",
            "role": "Ciska",
            "person": {
                "+content": "Paul St. Peter",
                "+@id": "4824"
            }
        },
        {
            "+@gid": "2260353309",
            "+@lang": "EN",
            "role": "Jugai",
            "person": {
                "+content": "Patrick Seitz",
                "+@id": "7108"
            }
        },
        {
            "+@gid": "1681260042",
            "+@lang": "EN",
            "role": "Amo",
            "person": {
                "+content": "Xanthe Huynh",
                "+@id": "69839"
            }
        },
        {
            "+@gid": "3300199057",
            "+@lang": "EN",
            "role": "Yuria",
            "person": {
                "+content": "Alexis Tipton",
                "+@id": "77434"
            }
        },
        {
            "+@gid": "3994783983",
            "+@lang": "EN",
            "role": "Saya",
            "person": {
                "+content": "Emily Neves",
                "+@id": "83471"
            }
        },
        {
            "+@gid": "2373762345",
            "+@lang": "EN",
            "role": "Shin",
            "person": {
                "+content": "Christopher Wehkamp",
                "+@id": "112286"
            }
        },
        {
            "+@gid": "3379936593",
            "+@lang": "EN",
            "role": "Kenshiro",
            "person": {
                "+content": "Robbie Daymond",
                "+@id": "127931"
            }
        },
        {
            "+@gid": "2619633643",
            "+@lang": "EN",
            "role": "Dan",
            "person": {
                "+content": "Dawn M. Bennett",
                "+@id": "130217"
            }
        },
        {
            "+@gid": "1181932067",
            "+@lang": "EN",
            "role": "Z",
            "person": {
                "+content": "Christian Thorsen",
                "+@id": "207164"
            }
        },
        {
            "+@gid": "635662700",
            "+@lang": "EN",
            "role": "Gades",
            "person": {
                "+content": "Richard Barcenas",
                "+@id": "253193"
            }
        },
        {
            "+@gid": "3458512913",
            "+@lang": "FR",
            "role": "Kenshirô",
            "person": {
                "+content": "Frédéric Souterelle",
                "+@id": "55617"
            }
        },
        {
            "+@gid": "1625874325",
            "+@lang": "FR",
            "role": "Julia",
            "person": {
                "+content": "Marie Diot",
                "+@id": "57450"
            }
        },
        {
            "+@gid": "1905276693",
            "+@lang": "IT",
            "role": "Shin",
            "person": {
                "+content": "Claudio Ridolfo",
                "+@id": "18116"
            }
        },
        {
            "+@gid": "2427345747",
            "+@lang": "IT",
            "role": "Fuugen",
            "person": {
                "+content": "Mario Scarabelli",
                "+@id": "25940"
            }
        },
        {
            "+@gid": "2653861967",
            "+@lang": "IT",
            "role": "Jugai",
            "person": {
                "+content": "Massimiliano Lotti",
                "+@id": "25985"
            }
        },
        {
            "+@gid": "3463255089",
            "+@lang": "IT",
            "role": "Ryuken",
            "person": {
                "+content": "Maurizio Scattorin",
                "+@id": "25993"
            }
        },
        {
            "+@gid": "807559383",
            "+@lang": "IT",
            "role": "Guruma",
            "person": {
                "+content": "Sergio Romanò",
                "+@id": "26034"
            }
        },
        {
            "+@gid": "2888489769",
            "+@lang": "IT",
            "role": "Siska",
            "person": {
                "+content": "Giovanni Battezzato",
                "+@id": "26041"
            }
        },
        {
            "+@gid": "2625347449",
            "+@lang": "IT",
            "role": "Julia",
            "person": {
                "+content": "Patrizia Mottola",
                "+@id": "26258"
            }
        },
        {
            "+@gid": "1599116631",
            "+@lang": "IT",
            "role": "Kenshiro",
            "person": {
                "+content": "Lorenzo Scattorin",
                "+@id": "39848"
            }
        },
        {
            "+@gid": "1325980950",
            "+@lang": "IT",
            "role": "Dan",
            "person": {
                "+content": "Annalisa Longo",
                "+@id": "80578"
            }
        },
        {
            "+@gid": "3812726400",
            "+@lang": "JA",
            "role": "Jinia",
            "person": {
                "+content": "Shigeru Chiba",
                "+@id": "427"
            }
        },
        {
            "+@gid": "1676974239",
            "+@lang": "JA",
            "role": "Fūgen",
            "person": {
                "+content": "Takeshi Aono",
                "+@id": "956"
            }
        },
        {
            "+@gid": "2399257999",
            "+@lang": "JA",
            "role": "Yaman",
            "person": {
                "+content": "Keiichi Nanba",
                "+@id": "1019"
            }
        },
        {
            "+@gid": "3862309032",
            "+@lang": "JA",
            "role": "Guruma",
            "person": {
                "+content": "Tesshō Genda",
                "+@id": "1250"
            }
        },
        {
            "+@gid": "2523606574",
            "+@lang": "JA",
            "role": "Ciska",
            "person": {
                "+content": "Shōzō Iizuka",
                "+@id": "1259"
            }
        },
        {
            "+@gid": "2427320823",
            "+@lang": "JA",
            "role": "Saya",
            "person": {
                "+content": "Miina Tominaga",
                "+@id": "1584"
            }
        },
        {
            "+@gid": "3153698302",
            "+@lang": "JA",
            "role": "Yuria",
            "person": {
                "+content": "Yuriko Ishida",
                "+@id": "2038"
            }
        },
        {
            "+@gid": "1685984526",
            "+@lang": "JA",
            "role": "Ryūken",
            "person": {
                "+content": "Chikao Ōtsuka",
                "+@id": "2171"
            }
        },
        {
            "+@gid": "1946006771",
            "+@lang": "JA",
            "role": "Dan",
            "person": {
                "+content": "Romi Park",
                "+@id": "5108"
            }
        },
        {
            "+@gid": "2229550877",
            "+@lang": "JA",
            "role": "Gades",
            "person": {
                "+content": "Tetsu Inada",
                "+@id": "7015"
            }
        },
        {
            "+@gid": "1867099828",
            "+@lang": "JA",
            "role": "Jugai",
            "person": {
                "+content": "Rikiya Koyama",
                "+@id": "8136"
            }
        },
        {
            "+@gid": "2203388361",
            "+@lang": "JA",
            "role": "Amo",
            "person": {
                "+content": "Hiromi Konno",
                "+@id": "8217"
            }
        },
        {
            "+@gid": "1099329649",
            "+@lang": "JA",
            "role": "Shin",
            "person": {
                "+content": "Takuya Kirimoto",
                "+@id": "20353"
            }
        },
        {
            "+@gid": "3739452514",
            "+@lang": "JA",
            "role": "Kenshirō",
            "person": {
                "+content": "Hiroshi Abe",
                "+@id": "24434"
            }
        }
    ],
    "credit": [
        {
            "+@gid": "722154627",
            "task": "Animation Production",
            "company": {
                "+content": "Tokyo Movie",
                "+@id": "1555"
            }
        },
        {
            "+@gid": "1014963879",
            "task": "Production",
            "company": {
                "+content": "TMS Entertainment",
                "+@id": "292"
            }
        },
        {
            "+@gid": "3658928065",
            "task": "Production",
            "company": {
                "+content": "North Stars Pictures",
                "+@id": "4686"
            }
        }
    ],
    "+@date-added": "2005-02-27T11:43:59Z",
    "+@date-last-modified-at": "2024-12-04T20:21:55Z",
    "+@date-last-updated-at": "2024-12-04T20:21:55Z"
}