{
    "+@id": "10083",
    "+@gid": "383289796",
    "+@type": "manga",
    "+@name": "Manga Abenobashi Mahō Shōtengai - Abeno no Machi ni Inori o Komete",
    "+@precision": "manga",
    "+@generated-on": "2025-03-17T23:28:35Z",
    "related-prev": {
        "+@rel": "serialized in",
        "+@id": "4665"
    },
    "related-next": {
        "+@id": "820",
        "+@rel": "adaptation"
    },
    "info": [
        {
            "+@gid": "1870589172",
            "+@type": "Picture",
            "+@src": "https://cdn.animenewsnetwork.com/thumbnails/fit200x200/encyc/A10083-3.jpg",
            "+@width": "200",
            "+@height": "200",
            "img": [
                {
                    "+@src": "https://cdn.animenewsnetwork.com/thumbnails/fit200x200/encyc/A10083-3.jpg",
                    "+@width": "200",
                    "+@height": "200"
                },
                {
                    "+@src": "https://cdn.animenewsnetwork.com/thumbnails/max500x600/encyc/A10083-3.jpg",
                    "+@width": "280",
                    "+@height": "280"
                }
            ]
        },
        {
            "+content": "Manga Abenobashi Mahō Shōtengai - Abeno no Machi ni Inori o Komete",
            "+@gid": "2907232468",
            "+@type": "Main title",
            "+@lang": "JA"
        },
        {
            "+content": "まんが アベノ橋魔法☆商店街 ―アベノの街に祈りを込めて―",
            "+@gid": "2296341814",
            "+@type": "Alternative title",
            "+@lang": "JA"
        },
        {
            "+content": "1",
            "+@gid": "2018201371",
            "+@type": "Number of tankoubon"
        },
        {
            "+content": "194",
            "+@gid": "1489323321",
            "+@type": "Number of pages"
        },
        {
            "+content": "2001-07-25 (serialized in Afternoon)",
            "+@gid": "3238142589",
            "+@type": "Vintage"
        }
    ],
    "ratings": {
        "+@nb_votes": "2",
        "+@weighted_score": "2.238"
    },
    "staff": {
        "+@gid": "2131467173",
        "task": "Story & Art",
        "person": {
            "+content": "Kenji Tsuruta",
            "+@id": "5021"
        }
    },
    "+@date-added": "2008-06-18T12:14:01Z",
    "+@date-last-modified-at": "2025-03-17T23:28:36Z",
    "+@date-last-updated-at": "2025-03-17T23:28:36Z"
}