{
    "+@id": "15779",
    "+@gid": "2515626467",
    "+@type": "manga",
    "+@name": "Donten ni Warau",
    "+@precision": "manga",
    "+@generated-on": "2025-01-13T10:35:26Z",
    "related-prev": {
        "+@rel": "serialized in",
        "+@id": "12978"
    },
    "related-next": [
        {
            "+@id": "15780",
            "+@rel": "adaptation"
        },
        {
            "+@id": "19804",
            "+@rel": "side story"
        },
        {
            "+@id": "22205",
            "+@rel": "prequel"
        },
        {
            "+@id": "22206",
            "+@rel": "prequel"
        }
    ],
    "info": [
        {
            "+@gid": "321281535",
            "+@type": "Picture",
            "+@src": "https://cdn.animenewsnetwork.com/thumbnails/fit200x200/encyc/A15779-321281535.1403940848.jpg",
            "+@width": "200",
            "+@height": "150",
            "img": [
                {
                    "+@src": "https://cdn.animenewsnetwork.com/thumbnails/fit200x200/encyc/A15779-321281535.1403940848.jpg",
                    "+@width": "200",
                    "+@height": "150"
                },
                {
                    "+@src": "https://cdn.animenewsnetwork.com/thumbnails/max500x600/encyc/A15779-321281535.1403940848.jpg",
                    "+@width": "500",
                    "+@height": "375"
                },
                {
                    "+@src": "https://cdn.animenewsnetwork.com/images/encyc/A15779-321281535.1403940848.jpg",
                    "+@width": "512",
                    "+@height": "384"
                }
            ]
        },
        {
            "+content": "Donten ni Warau",
            "+@gid": "2904000227",
            "+@type": "Main title",
            "+@lang": "JA"
        },
        {
            "+content": "Laughing Under the Clouds",
            "+@gid": "1848890328",
            "+@type": "Alternative title",
            "+@lang": "EN"
        },
        {
            "+content": "Ridendo tra le nuvole",
            "+@gid": "1012503355",
            "+@type": "Alternative title",
            "+@lang": "IT"
        },
        {
            "+content": "Riendo bajo las nubes",
            "+@gid": "1411431176",
            "+@type": "Alternative title",
            "+@lang": "ES"
        },
        {
            "+content": "Śmiech w chmurach: Donten ni Warau",
            "+@gid": "3431391078",
            "+@type": "Alternative title",
            "+@lang": "PL"
        },
        {
            "+content": "曇天に笑う",
            "+@gid": "1679577738",
            "+@type": "Alternative title",
            "+@lang": "JA"
        },
        {
            "+content": "笑傲曇天",
            "+@gid": "3397557028",
            "+@type": "Alternative title",
            "+@lang": "ZH-TW"
        },
        {
            "+content": "action",
            "+@gid": "557589206",
            "+@type": "Genres"
        },
        {
            "+content": "supernatural",
            "+@gid": "2353149374",
            "+@type": "Genres"
        },
        {
            "+content": "historical",
            "+@gid": "625441621",
            "+@type": "Themes"
        },
        {
            "+content": "revenge",
            "+@gid": "2117029541",
            "+@type": "Themes"
        },
        {
            "+content": "samurai",
            "+@gid": "837870583",
            "+@type": "Themes"
        },
        {
            "+content": "twins",
            "+@gid": "873125113",
            "+@type": "Themes"
        },
        {
            "+content": "6",
            "+@gid": "2929245768",
            "+@type": "Number of tankoubon"
        },
        {
            "+content": "171",
            "+@gid": "702636162",
            "+@type": "Number of pages"
        },
        {
            "+content": "2011-02-15 to 2013-05-15 (serialized in <i>Monthly Comic Avarus</i>)",
            "+@gid": "2174326416",
            "+@type": "Vintage"
        },
        {
            "+content": "曇天に笑う",
            "+@gid": "3219601360",
            "+@type": "Official website",
            "+@lang": "JA",
            "+@href": "http://www.mag-garden.co.jp/donten/"
        }
    ],
    "ratings": {
        "+@nb_votes": "5",
        "+@weighted_score": "7.5442",
        "+@bayesian_score": "7.60811"
    },
    "release": [
        {
            "+content": "Laughing Under the Clouds (GN 1)",
            "+@date": "2021-04-30",
            "+@href": "https://www.animenewsnetwork.com/encyclopedia/releases.php?id=41514"
        },
        {
            "+content": "Laughing Under the Clouds (GN 2)",
            "+@date": "2021-07-06",
            "+@href": "https://www.animenewsnetwork.com/encyclopedia/releases.php?id=41515"
        },
        {
            "+content": "Laughing Under the Clouds (GN 3)",
            "+@date": "2021-08-03",
            "+@href": "https://www.animenewsnetwork.com/encyclopedia/releases.php?id=41516"
        },
        {
            "+content": "Laughing Under the Clouds (GN 4)",
            "+@date": "2021-10-05",
            "+@href": "https://www.animenewsnetwork.com/encyclopedia/releases.php?id=41517"
        },
        {
            "+content": "Laughing Under the Clouds (GN 5)",
            "+@date": "2021-12-21",
            "+@href": "https://www.animenewsnetwork.com/encyclopedia/releases.php?id=48904"
        },
        {
            "+content": "Laughing Under the Clouds (GN 6)",
            "+@date": "2022-02-01",
            "+@href": "https://www.animenewsnetwork.com/encyclopedia/releases.php?id=47758"
        }
    ],
    "news": [
        {
            "+content": "Japan's Animation DVD Ranking, May 11-17",
            "+@datetime": "2015-05-19T08:55:00Z",
            "+@href": "https://www.animenewsnetwork.com:/news/2015-05-19/japan-animation-dvd-ranking-may-11-17/.88319"
        },
        {
            "+content": "Japanese Comic Ranking, May 25-31",
            "+@datetime": "2015-06-03T20:40:00Z",
            "+@href": "https://www.animenewsnetwork.com:/news/2015-06-03/japanese-comic-ranking-may-25-31/.88879"
        },
        {
            "+content": "Japanese Comic Ranking, June 1-7",
            "+@datetime": "2015-06-10T21:30:00Z",
            "+@href": "https://www.animenewsnetwork.com:/news/2015-06-10/japanese-comic-ranking-june-1-7/.89116"
        },
        {
            "+content": "<cite>Laughing Under the Clouds</cite> Manga Gets Live-Action Film Adaptation",
            "+@datetime": "2016-05-30T05:20:00Z",
            "+@href": "https://www.animenewsnetwork.com:/news/2016-05-30/laughing-under-the-clouds-manga-gets-live-action-film-adaptation/.102649"
        },
        {
            "+content": "<cite>Laughing Under the Clouds</cite> Live-Action Film Casts Sōta Fukushi",
            "+@datetime": "2016-07-04T03:38:35Z",
            "+@href": "https://www.animenewsnetwork.com:/news/2016-07-03/laughing-under-the-clouds-live-action-film-casts-sota-fukushi/.103934"
        },
        {
            "+content": "<cite>Laughing Under the Clouds</cite> Live-Action Film Casts Yūma Nakayama, Kirato Wakayama",
            "+@datetime": "2016-08-08T07:45:00Z",
            "+@href": "https://www.animenewsnetwork.com:/news/2016-08-08/laughing-under-the-clouds-live-action-film-casts-yuma-nakayama-kirato-wakayama/.105128"
        },
        {
            "+content": "Live-Action <cite>Laughing Under the Clouds</cite> Film Casts Renn Kiriyama, Yūki Furukawa",
            "+@datetime": "2016-08-25T01:35:00Z",
            "+@href": "https://www.animenewsnetwork.com:/news/2016-08-24/live-action-laughing-under-the-clouds-film-casts-renn-kiriyama-yuki-furukawa/.105735"
        },
        {
            "+content": "Live-Action <cite>Laughing Under the Clouds</cite> Film Casts Shunsuke Daito",
            "+@datetime": "2016-09-03T17:00:00Z",
            "+@href": "https://www.animenewsnetwork.com:/news/2016-09-03/live-action-laughing-under-the-clouds-film-casts-shunsuke-daito/.105969"
        },
        {
            "+content": "Live-Action <cite>Laughing Under the Clouds</cite> Film Casts Yūta Koseki",
            "+@datetime": "2016-09-08T08:30:00Z",
            "+@href": "https://www.animenewsnetwork.com:/news/2016-09-08/live-action-laughing-under-the-clouds-film-casts-yuta-koseki/.106220"
        },
        {
            "+content": "Live-Action <cite>Laughing Under the Clouds</cite> Adds 4 New Cast Members",
            "+@datetime": "2016-09-29T07:15:00Z",
            "+@href": "https://www.animenewsnetwork.com:/news/2016-09-29/live-action-laughing-under-the-clouds-adds-4-new-cast-members/.107023"
        },
        {
            "+content": "<cite>Laughing Under the Clouds/Donten ni Warau Gaiden</cite> Manga Ends",
            "+@datetime": "2017-02-02T22:00:00Z",
            "+@href": "https://www.animenewsnetwork.com:/news/2017-02-02/laughing-under-the-clouds-donten-ni-warau-gaiden-manga-ends/.111791"
        },
        {
            "+content": "<cite>Laughing Under the Clouds/Donten ni Warau</cite> Side Story Manga Gets Anime",
            "+@datetime": "2017-03-13T04:15:00Z",
            "+@href": "https://www.animenewsnetwork.com:/news/2017-03-13/laughing-under-the-clouds-donten-ni-warau-side-story-manga-gets-anime/.113340"
        },
        {
            "+content": "<cite>Attack on Titan's</cite> WIT Animates <cite>Laughing Under the Clouds</cite> Film",
            "+@datetime": "2017-03-14T04:00:00Z",
            "+@href": "https://www.animenewsnetwork.com:/news/2017-03-14/attack-on-titan-wit-animates-laughing-under-the-clouds-film/.113393"
        },
        {
            "+content": "Japanese Comic Ranking, March 13-19",
            "+@datetime": "2017-03-22T20:30:00Z",
            "+@href": "https://www.animenewsnetwork.com:/news/2017-03-22/japanese-comic-ranking-march-13-19/.113769"
        },
        {
            "+content": "1st <cite>Laughing Under the Clouds Gaiden</cite> Anime Film's Teaser Reveals Cast, December Opening",
            "+@datetime": "2017-06-29T06:45:00Z",
            "+@href": "https://www.animenewsnetwork.com:/news/2017-06-29/1st-laughing-under-the-clouds-gaiden-anime-film-teaser-reveals-cast-december-opening/.118160"
        },
        {
            "+content": "<cite>Laughing Under the Clouds</cite> Manga Gets Live-Action Spinoff Work",
            "+@datetime": "2017-12-02T07:45:00Z",
            "+@href": "https://www.animenewsnetwork.com:/news/2017-12-02/laughing-under-the-clouds-manga-gets-live-action-spinoff-work/.124766"
        },
        {
            "+content": "<Cite>Laughing Under the Clouds Gaiden</cite> 2nd Anime Film's Trailer Highlights Fūma Twins",
            "+@datetime": "2018-03-07T12:15:00Z",
            "+@href": "https://www.animenewsnetwork.com:/news/2018-03-07/laughing-under-the-clouds-gaiden-2nd-anime-film-trailer-highlights-fuma-twins/.128617"
        },
        {
            "+content": "Japan's Animation Blu-ray Disc Ranking, September 10-16",
            "+@datetime": "2018-09-18T08:55:04Z",
            "+@href": "https://www.animenewsnetwork.com:/news/2018-09-18/japan-animation-blu-ray-disc-ranking-september-10-16/.136941"
        },
        {
            "+content": "Japan's Animation DVD Ranking, September 10-16",
            "+@datetime": "2018-09-18T09:15:58Z",
            "+@href": "https://www.animenewsnetwork.com:/news/2018-09-18/japan-animation-dvd-ranking-september-10-16/.136943"
        },
        {
            "+content": "Kemuri Karakara Launches New Short <cite>Laughing Under the Clouds</cite> Manga",
            "+@datetime": "2018-10-05T13:33:36Z",
            "+@href": "https://www.animenewsnetwork.com:/news/2018-10-05/kemuri-karakara-launches-new-short-laughing-under-the-clouds-manga/.137705"
        },
        {
            "+content": "Tokyopop Adds <cite>Laughing Under the Clouds</cite>, 5 More Manga",
            "+@datetime": "2020-11-24T05:15:00Z",
            "+@href": "https://www.animenewsnetwork.com:/news/2020-11-24/tokyopop-adds-laughing-under-the-clouds-5-more-manga/.166597"
        },
        {
            "+content": "Manga Briefs Roundup: March-April 2021",
            "+@datetime": "2021-04-04T16:02:00Z",
            "+@href": "https://www.animenewsnetwork.com:/news/2021-04-04/manga-briefs-roundup-march-april-2021/.171449"
        },
        {
            "+content": "North American Anime, Manga Releases, April 18-24",
            "+@datetime": "2021-04-20T21:00:00Z",
            "+@href": "https://www.animenewsnetwork.com:/news/2021-04-20/north-american-anime-manga-releases-april-18-24/.171951"
        },
        {
            "+content": "North American Anime, Manga Releases, July 4-10",
            "+@datetime": "2021-07-06T21:00:00Z",
            "+@href": "https://www.animenewsnetwork.com:/news/2021-07-06/north-american-anime-manga-releases-july-4-10/.174863"
        },
        {
            "+content": "North American Anime, Manga Releases, August 1-7",
            "+@datetime": "2021-08-03T20:35:00Z",
            "+@href": "https://www.animenewsnetwork.com:/news/2021-08-03/north-american-anime-manga-releases-august-1-7/.175862"
        },
        {
            "+content": "North American Anime, Manga Releases, October 3-9",
            "+@datetime": "2021-10-05T21:00:18Z",
            "+@href": "https://www.animenewsnetwork.com:/news/2021-10-05/north-american-anime-manga-releases-october-3-9/.178176"
        },
        {
            "+content": "North American Anime, Manga Releases, December 5-11",
            "+@datetime": "2021-12-07T22:00:00Z",
            "+@href": "https://www.animenewsnetwork.com:/news/2021-12-07/north-american-anime-manga-releases-december-5-11/.180377"
        },
        {
            "+content": "North American Anime, Manga Releases, December 19-25",
            "+@datetime": "2021-12-21T22:00:00Z",
            "+@href": "https://www.animenewsnetwork.com:/news/2021-12-21/north-american-anime-manga-releases-december-19-25/.180876"
        },
        {
            "+content": "North American Anime, Manga Releases, January 30-February 5",
            "+@datetime": "2022-02-01T21:30:00Z",
            "+@href": "https://www.animenewsnetwork.com:/news/2022-02-01/north-american-anime-manga-releases-january-30-february-5/.182129"
        }
    ],
    "staff": {
        "+@gid": "3061884630",
        "task": "Story & Art",
        "person": {
            "+content": "Karakarakemuri",
            "+@id": "101556"
        }
    },
    "+@date-added": "2013-12-24T16:08:48Z",
    "+@date-last-modified-at": "2025-01-13T10:35:29Z",
    "+@date-last-updated-at": "2025-01-13T10:35:29Z"
}