{
    "+@id": "16384",
    "+@gid": "1052847211",
    "+@type": "manga",
    "+@name": "My Dear Prince",
    "+@precision": "manga",
    "+@generated-on": "2024-12-04T21:43:01Z",
    "info": [
        {
            "+@gid": "2287109662",
            "+@type": "Picture",
            "+@src": "https://cdn.animenewsnetwork.com/thumbnails/fit200x200/encyc/A16384-2287109662.1414888598.jpg",
            "+@width": "139",
            "+@height": "200",
            "img": [
                {
                    "+@src": "https://cdn.animenewsnetwork.com/thumbnails/fit200x200/encyc/A16384-2287109662.1414888598.jpg",
                    "+@width": "139",
                    "+@height": "200"
                },
                {
                    "+@src": "https://cdn.animenewsnetwork.com/thumbnails/max500x600/encyc/A16384-2287109662.1414888598.jpg",
                    "+@width": "208",
                    "+@height": "300"
                }
            ]
        },
        {
            "+content": "My Dear Prince",
            "+@gid": "661155706",
            "+@type": "Main title",
            "+@lang": "EN"
        },
        {
            "+content": "Ōjito",
            "+@gid": "3040767540",
            "+@type": "Alternative title",
            "+@lang": "JA"
        },
        {
            "+content": "おうじと",
            "+@gid": "2856643673",
            "+@type": "Alternative title",
            "+@lang": "JA"
        },
        {
            "+content": "romance",
            "+@gid": "2876236914",
            "+@type": "Genres"
        },
        {
            "+content": "yaoi",
            "+@gid": "3966466587",
            "+@type": "Themes"
        },
        {
            "+content": "Tsukasa is the \"prince\" of his high school, both attractive and arrogant. Shinta is an all-around average high school boy. Yet, something about Shinta captures Tsukasa's heart.",
            "+@gid": "1823339754",
            "+@type": "Plot Summary"
        },
        {
            "+content": "1",
            "+@gid": "1154553419",
            "+@type": "Number of tankoubon"
        },
        {
            "+content": "2010",
            "+@gid": "2416750023",
            "+@type": "Vintage"
        }
    ],
    "news": {
        "+content": "JManga Adds Fumi Tomoe's <cite>My Dear Prince</cite> Boys-Love Manga",
        "+@datetime": "2012-08-30T21:15:00Z",
        "+@href": "https://www.animenewsnetwork.com/news/2012-08-30/jmanga-adds-fumi-tomoe-my-dear-prince-boys-love-manga"
    },
    "staff": {
        "+@gid": "1762827748",
        "task": "Story & Art",
        "person": {
            "+content": "Fumi Tomoe",
            "+@id": "132244"
        }
    },
    "+@date-added": "2014-11-01T20:30:12Z",
    "+@date-last-modified-at": "2024-12-04T21:43:00Z",
    "+@date-last-updated-at": "2024-12-04T21:43:00Z"
}