{
    "+@id": "23818",
    "+@gid": "1896716191",
    "+@type": "manga",
    "+@name": "Black-Haired Kerry and the Casebook of Romantic Troubles",
    "+@precision": "manga",
    "+@generated-on": "2025-03-10T15:31:16Z",
    "info": [
        {
            "+@gid": "1303951218",
            "+@type": "Picture",
            "+@src": "https://cdn.animenewsnetwork.com/thumbnails/fit200x200/encyc/A23818-1303951218.1607107936.jpg",
            "+@width": "141",
            "+@height": "200",
            "img": [
                {
                    "+@src": "https://cdn.animenewsnetwork.com/thumbnails/fit200x200/encyc/A23818-1303951218.1607107936.jpg",
                    "+@width": "141",
                    "+@height": "200"
                },
                {
                    "+@src": "https://cdn.animenewsnetwork.com/thumbnails/max500x600/encyc/A23818-1303951218.1607107936.jpg",
                    "+@width": "206",
                    "+@height": "292"
                }
            ]
        },
        {
            "+content": "Black-Haired Kerry and the Casebook of Romantic Troubles",
            "+@gid": "1704657540",
            "+@type": "Main title",
            "+@lang": "EN"
        },
        {
            "+content": "Kurokami no Lady to Koi no Jikenbo",
            "+@gid": "2712720147",
            "+@type": "Alternative title",
            "+@lang": "JA"
        },
        {
            "+content": "黒髪のレディと恋の事件簿",
            "+@gid": "2836432798",
            "+@type": "Alternative title",
            "+@lang": "JA"
        },
        {
            "+content": "In the 1890s, a young noblewoman, disgusted by the lack of rights for women and the lower classes, cuts off her hair and sets herself up as a private detective specializing in such cases. Joined by her friend Liz and later by handsome working-class lawyer Jutaro Hohen, Kerry disentangles the mysteries of those who hire her – and maybe even those of her heart.",
            "+@gid": "2937187307",
            "+@type": "Plot Summary"
        },
        {
            "+content": "2013",
            "+@gid": "3764645216",
            "+@type": "Vintage"
        }
    ],
    "review": {
        "+content": "Black-Haired Kerry and the Casebook of Romantic Troubles GN 1-3",
        "+@href": "https://www.animenewsnetwork.com/review/black-haired-kerry-and-the-casebook-of-romantic-troubles/gn-1-3/.167009"
    },
    "staff": {
        "+@gid": "3306322370",
        "task": "Story & Art",
        "person": {
            "+content": "Yuriko Matsukawa",
            "+@id": "74036"
        }
    },
    "+@date-added": "2020-12-04T13:51:45Z",
    "+@date-last-modified-at": "2025-03-10T15:31:19Z",
    "+@date-last-updated-at": "2025-03-10T15:31:19Z"
}