{
    "+@id": "5796",
    "+@gid": "2286498782",
    "+@type": "manga",
    "+@name": "Four Immigrants Manga",
    "+@precision": "manga",
    "+@generated-on": "2025-02-17T22:30:41Z",
    "info": [
        {
            "+@gid": "2882678815",
            "+@type": "Picture",
            "+@src": "https://cdn.animenewsnetwork.com/thumbnails/fit200x200/encyc/A5796-13.jpg",
            "+@width": "128",
            "+@height": "200",
            "img": {
                "+@src": "https://cdn.animenewsnetwork.com/thumbnails/fit200x200/encyc/A5796-13.jpg",
                "+@width": "128",
                "+@height": "200"
            }
        },
        {
            "+content": "The Four Immigrants Manga",
            "+@gid": "1991503793",
            "+@type": "Main title",
            "+@lang": "EN"
        },
        {
            "+content": "Manga of the Four Students",
            "+@gid": "2515754534",
            "+@type": "Alternative title",
            "+@lang": "EN"
        },
        {
            "+content": "Manga Yonin Shosei",
            "+@gid": "1696623523",
            "+@type": "Alternative title",
            "+@lang": "JA"
        },
        {
            "+content": "The Four Immigrants Manga - A Japanese Experience in San Francisco 1904-1924",
            "+@gid": "1203758872",
            "+@type": "Alternative title",
            "+@lang": "EN"
        },
        {
            "+content": "漫画四人書生",
            "+@gid": "2618209597",
            "+@type": "Alternative title",
            "+@lang": "JA"
        },
        {
            "+content": "comedy",
            "+@gid": "914738942",
            "+@type": "Genres"
        },
        {
            "+content": "slice of life",
            "+@gid": "1887018487",
            "+@type": "Genres"
        },
        {
            "+content": "historical",
            "+@gid": "1747385996",
            "+@type": "Themes"
        },
        {
            "+content": "Four young Japanese men immigrate to San Francisco at the start of the 20th century. There they adopt American names and set out to learn western ways and seek their fortunes. Henry (the author’s alter ego) enrolls in art school to learn the western style of painting, Charlie studies American democracy, Fred plans to become a successful farmer, and Frank wants to be a prosperous merchant. Along the way they experience first hand the events affecting Northern California and the United States at that time; the 1906 earthquake, the World’s Fair, and World War I.",
            "+@gid": "1938537939",
            "+@type": "Plot Summary"
        },
        {
            "+content": "1931-03-03",
            "+@gid": "2332404441",
            "+@type": "Vintage"
        },
        {
            "+content": "Frederik L. Schodt's The Four Immigrants Manga webpage",
            "+@gid": "2788425720",
            "+@type": "Official website",
            "+@lang": "EN",
            "+@href": "http://www.jai2.com/HK.htm"
        }
    ],
    "ratings": {
        "+@nb_votes": "8",
        "+@weighted_score": "7.4752",
        "+@bayesian_score": "7.54597"
    },
    "release": {
        "+content": "The Four Immigrants Manga (GN)",
        "+@date": "1998-10-01",
        "+@href": "https://www.animenewsnetwork.com/encyclopedia/releases.php?id=22887"
    },
    "news": [
        {
            "+content": "<cite>The Four Immigrants Manga</cite> Gets Stage Musical",
            "+@datetime": "2016-12-21T17:40:00Z",
            "+@href": "https://www.animenewsnetwork.com:/news/2016-12-21/the-four-immigrants-manga-gets-stage-musical/.110196"
        },
        {
            "+content": "<cite>Blue Giant Explorer, Chainsaw Man, The Fable</cite>, More Manga Nominated for Angoulême",
            "+@datetime": "2023-12-30T03:26:26Z",
            "+@href": "https://www.animenewsnetwork.com:/news/2023-12-29/blue-giant-explorer-chainsaw-man-the-fable-more-manga-nominated-for-angouleme/.206054"
        }
    ],
    "+@date-added": "2005-08-08T18:45:41Z",
    "+@date-last-modified-at": "2025-02-17T22:30:42Z",
    "+@date-last-updated-at": "2025-02-17T22:30:42Z"
}